[
  {
    "TokenID": "asset_registry/548efa1d3486b7caa31fc778eec1983f34a96502",
    "TokenSymbol": "KINT",
    "Logo": "../logos/bifrost-kusama_custom_KINT.png",
    "Description (en)": "",
    "Description (zh)": "",
    "Website Link": "",
    "Twitter Link": "",
    "Telegram Link": "",
    "Discord Link": "",
    "Medium Link": "",
    "Github Link": "",
    "Category": "custom",
    "Coingecko API ID": "kintsugi",
    "Network": "bifrost-kusama"
  },
  {
    "TokenID": "asset_registry/42143ac2073520066e25b865fbf26a7fe57b9715",
    "TokenSymbol": "KSM",
    "Logo": "../logos/bifrost-kusama_custom_KSM.png",
    "Description (en)": "",
    "Description (zh)": "",
    "Website Link": "",
    "Twitter Link": "",
    "Telegram Link": "",
    "Discord Link": "",
    "Medium Link": "",
    "Github Link": "",
    "Category": "custom",
    "Coingecko API ID": "kusama",
    "Network": "bifrost-kusama"
  },
  {
    "TokenID": "asset_registry/3279ef23c7534c3f20a3390c671b563bfe68e2a9",
    "TokenSymbol": "MOVR",
    "Logo": "../logos/bifrost-kusama_custom_MOVR.png",
    "Description (en)": "",
    "Description (zh)": "",
    "Website Link": "",
    "Twitter Link": "",
    "Telegram Link": "",
    "Discord Link": "",
    "Medium Link": "",
    "Github Link": "",
    "Category": "custom",
    "Coingecko API ID": "moonriver",
    "Network": "bifrost-kusama"
  },
  {
    "TokenID": "asset_registry/f66a5cfd4ed4c4ba9d6506130b034d9bc3fe75ff",
    "TokenSymbol": "ZLK",
    "Logo": "../logos/bifrost-kusama_custom_ZLK.png",
    "Description (en)": "",
    "Description (zh)": "",
    "Website Link": "",
    "Twitter Link": "",
    "Telegram Link": "",
    "Discord Link": "",
    "Medium Link": "",
    "Github Link": "",
    "Category": "custom",
    "Coingecko API ID": "zenlink-network-token",
    "Network": "bifrost-kusama"
  },
  {
    "TokenID": "asset_registry/551a80e79e02213dd918190892af5034002909c5",
    "TokenSymbol": "USDT",
    "Logo": "../logos/assethub-polkadot_asset_USDt.svg",
    "Description (en)": "",
    "Description (zh)": "",
    "Website Link": "",
    "Twitter Link": "",
    "Telegram Link": "",
    "Discord Link": "",
    "Medium Link": "",
    "Github Link": "",
    "Category": "custom",
    "Coingecko API ID": "tether",
    "Network": "bifrost-kusama"
  }
]